pweb/__init__.py
pweb/pweb_engine.py
pweb/system12/__init__.py
pweb/system12/pweb_app_config.py
pweb/system12/pweb_app_hook.py
pweb/system12/pweb_base.py
pweb/system12/pweb_bismillah.py
pweb/system12/pweb_cache.py
pweb/system12/pweb_interfaces.py
pweb/system12/pweb_module_cli.py
pweb/system12/pweb_module_manager.py
pweb/system12/pweb_registry.py
pweb/system12/pweb_saas_registry.py
pwebb-0.0.16.dist-info/LICENSE
pwebb-0.0.16.dist-info/METADATA
pwebb-0.0.16.dist-info/WHEEL
pwebb-0.0.16.dist-info/top_level.txt
pwebb-0.0.16.dist-info/RECORD
