Metadata-Version: 2.1
Name: pwebb
Version: 0.0.16
Summary: Python Web Boot (PWebB). PWebB is a DRY full-stack framework based on Flask micro web framework.
Home-page: https://github.com/banglafighter/pweb
Author: Bangla Fighter
Author-email: banglafighter.com@gmail.com
License: Apache 2.0
Platform: any
Classifier: Intended Audience :: Developers
Classifier: License :: OSI Approved :: Apache Software License
Classifier: Programming Language :: Python
License-File: LICENSE
Requires-Dist: Flask ==3.0.0
Requires-Dist: Flask-Cors ==4.0.0
Requires-Dist: ppy-common
Requires-Dist: pweb-orm
Requires-Dist: pweb-form-rest
Requires-Dist: pweb-cli
Requires-Dist: ppy-jsonyml
